{
  "students": [
    {
      "id": "mark dacer",
      "description": "afjdsg",
      "title": "afjdsg"
    },
     {
      "id": "juan cruz",
      "description": "afjdsg",
      "title": "mjn"
    } ,
    {
      "id": "3",
      "description": "afjdsg",
      "title": "afjdsg"
    },
     {
      "id": "juan 4",
      "description": "afjdsg",
      "title": "mjn"
    },  {
      "id": "mark 5",
      "description": "afjdsg",
      "title": "afjdsg"
    },
     {
      "id": "juan 6",
      "description": "afjdsg",
      "title": "mjn"
    }
    ]
}
